daddy_ai/__init__.py
daddy_ai/deploy_master.py
daddy_ai-0.20.0.dist-info/LICENSE
daddy_ai-0.20.0.dist-info/METADATA
daddy_ai-0.20.0.dist-info/WHEEL
daddy_ai-0.20.0.dist-info/top_level.txt
daddy_ai-0.20.0.dist-info/RECORD
