Metadata-Version: 2.1
Name: daddy-ai
Version: 0.20.0
Summary: A package for deploying and managing commands.
Home-page: https://linkedin.com/in/rajeshroy402
Author: Rajesh Roy
Author-email: rajeshroy402@gmail.com
Classifier: Programming Language :: Python :: 3
Classifier: License :: OSI Approved :: MIT License
Classifier: Operating System :: OS Independent
Requires-Python: >=3.6
License-File: LICENSE
